[{"idC":1,"nombre":"pakito","apellido":"lopez","telefono":"58348737","email":"fran@lopez.guerrero","dni":"2982132P","fechaNacimiento":"1999-11-17","cantidadReservasRealizadas":0,"multas":0,"estado":null},{"idC":2,"nombre":"kaisa","apellido":"farmiga","telefono":"5959595995595","email":"lasarga@lakaisa.laformiga","dni":"1029102902P","fechaNacimiento":"1996-12-18","cantidadReservasRealizadas":0,"multas":0,"estado":"Disponible"},{"idC":3,"nombre":"sascha","apellido":"pistacha","telefono":"6577474273","email":"sascha@esquizo.frenia","dni":"29313238P","fechaNacimiento":"2001-10-03","cantidadReservasRealizadas":0,"multas":0,"estado":"Disponible"},{"idC":4,"nombre":"maraya","apellido":"armario","telefono":"666555433","email":"lamaraya@portugois.obrigado","dni":"55566645W","fechaNacimiento":"2000-12-21","cantidadReservasRealizadas":0,"multas":0,"estado":"Activo"},{"idC":5,"nombre":"ivan","apellido":"ruiz","telefono":"676767676","email":"ivan@ruiz.rube","dni":"456787654J","fechaNacimiento":"1980-11-24","cantidadReservasRealizadas":0,"multas":0,"estado":"Activo"}]